setup.cfg
setup.py
pycpf/__init__.py
pycpf.egg-info/PKG-INFO
pycpf.egg-info/SOURCES.txt
pycpf.egg-info/dependency_links.txt
pycpf.egg-info/entry_points.txt
pycpf.egg-info/top_level.txt
pycpf.egg-info/zip-safe