Metadata-Version: 1.0
Name: pycpf
Version: 0.1
Summary: CPF generation and validation
Home-page: https://bitbucket.org/umgeher/pycpf
Author: Umgeher Taborda, Diogo Baeder
Author-email: umgeher@mitgnu.com
License: BSD 2-clause
Keywords: cpf validation generation
Platform: UNKNOWN
